distributions_jw369/Binomialdistribution.py
distributions_jw369/Gaussiandistribution.py
distributions_jw369/Generaldistribution.py
distributions_jw369/__init__.py
distributions_jw369-0.1.dist-info/DESCRIPTION.rst
distributions_jw369-0.1.dist-info/METADATA
distributions_jw369-0.1.dist-info/RECORD
distributions_jw369-0.1.dist-info/WHEEL
distributions_jw369-0.1.dist-info/metadata.json
distributions_jw369-0.1.dist-info/top_level.txt
